[
  {
    "subject": "Mathematics",
    "questions": [
      {
        "question": "The fifth term of the sequence (a_n = 2n - 3) is:",
        "options": [
          "13",
          "-13",
          "7",
          "-7"
        ],
        "answer": "7",
        "category": "unattempted",
        "selectedOption": ""
      },
      {
        "question": "The harmonic mean between (a) and (b) is:",
        "options": [
          "(a + b)/2",
          "±ab",
          "(a - b)/2",
          "2ab/(a + b)"
        ],
        "answer": "2ab/(a + b)",
        "category": "unattempted",
        "selectedOption": ""
      },
      {
        "question": "8! = 6!",
        "options": [
          "8",
          "1/56",
          "56",
          "None of these"
        ],
        "answer": "56",
        "category": "unattempted",
        "selectedOption": ""
      },
      {
        "question": "16C_{11} + 16C_{10} = __",
        "options": [
          "16C_{10}",
          "15C_{11}",
          "17C_{10}",
          "17C_{11}"
        ],
        "answer": "17C_{11}",
        "category": "unattempted",
        "selectedOption": ""
      },
      {
        "question": "In the expansion of (a + x)^n, the sum of exponents of (a) and (x) in each term of the expansion is:",
        "options": [
          "n + 1",
          "n - 1",
          "n",
          "2n"
        ],
        "answer": "n",
        "category": "unattempted",
        "selectedOption": ""
      },
      {
        "question": "([4/9]^(1/2)), the number of terms in the expansion of ((4/x^2) - 1)^(1/2) is:",
        "options": [
          "8",
          "9",
          "10",
          "11"
        ],
        "answer": "9",
        "category": "unattempted",
        "selectedOption": ""
      },
      {
        "question": "cos^2 θ + sin^2 θ = __",
        "options": [
          "2",
          "1/2",
          "1",
          "None of these"
        ],
        "answer": "1",
        "category": "unattempted",
        "selectedOption": ""
      },
      {
        "question": "Cos(2π + θ) = __",
        "options": [
          "Sin θ",
          "Cos θ",
          "-Sin θ",
          "-Cos θ"
        ],
        "answer": "Cos θ",
        "category": "unattempted",
        "selectedOption": ""
      },
      {
        "question": "2 sin a cos β = __",
        "options": [
          "Cos(a + β) - Cos(a - β)",
          "Cos(a + β) + Cos(a - β)",
          "Sin(a + β) - Sin(a - β)",
          "Sin(a + β) + Sin(a - β)"
        ],
        "answer": "Sin(a + β) + Sin(a - β)",
        "category": "unattempted",
        "selectedOption": ""
      },
      {
        "question": "Period of sin(3x) is:",
        "options": [
          "π/3",
          "π",
          "2π/3",
          "2π"
        ],
        "answer": "2π/3",
        "category": "unattempted",
        "selectedOption": ""
      },
      {
        "question": "Range of tan(x) is:",
        "options": [
          "ℝ",
          "[-1,1]",
          "(-∞, ∞)",
          "None of these"
        ],
        "answer": "(-∞, ∞)",
        "category": "unattempted",
        "selectedOption": ""
      },
      {
        "question": "The area of a sector of a circular region of radius (r) and central angle (θ) radians is:",
        "options": [
          "r^2/(2θ)",
          "1/(r^2θ)",
          "rθ",
          "1/2/(r^2θ)"
        ],
        "answer": "1/2/(r^2θ)",
        "category": "unattempted",
        "selectedOption": ""
      },
      {
        "question": "Sin(a) = __",
        "options": [
          "1",
          "-1",
          "1/2",
          "-1/2"
        ],
        "answer": "1/2",
        "category": "unattempted",
        "selectedOption": ""
      },
      {
        "question": "In ΔABC, R = __.",
        "options": [
          "a/s",
          "4Δ/abc",
          "s/(s-b)",
          "4Δ/s"
        ],
        "answer": "4Δ/abc",
        "category": "unattempted",
        "selectedOption": ""
      },
      {
        "question": "The solution of the equation 3tan^2 x = 1 is:",
        "options": [
          "{π + nπ : n ∈ ℤ}",
          "{π + 2nπ : n ∈ ℤ}",
          "{π + nπ : n ∈ ℤ}",
          "None of these"
        ],
        "answer": "{π + nπ : n ∈ ℤ}",
        "category": "unattempted",
        "selectedOption": ""
      },
      {
        "question": "If f(x) = x^3 - 2x^2 + 4x - 1 then f(0) is:",
        "options": [
          "0",
          "1",
          "-1",
          "None of these"
        ],
        "answer": "-1",
        "category": "unattempted",
        "selectedOption": ""
      },
      {
        "question": "F(x) = x is:",
        "options": [
          "Trigonometric function",
          "Exponential function",
          "Quadratic function",
          "None of these"
        ],
        "answer": "None of these",
        "category": "unattempted",
        "selectedOption": ""
      },
      {
        "question": "F(x) = tan x is:",
        "options": [
          "Even function",
          "Odd function",
          "Linear function",
          "None of these"
        ],
        "answer": "None of these",
        "category": "unattempted",
        "selectedOption": ""
      },
      {
        "question": "If f is a bijective function, then f(f^{-1}(x)) is:",
        "options": [
          "x",
          "0",
          "1",
          "-1"
        ],
        "answer": "x",
        "category": "unattempted",
        "selectedOption": ""
      },
      {
        "question": "lim(x -> 0) sin(ax)/sin(bx) = __.",
        "options": [
          "1",
          "b/a",
          "a/b",
          "None of these"
        ],
        "answer": "a/b",
        "category": "unattempted",
        "selectedOption": ""
      },
      {
        "question": "If f(x) = tan^{-1} x then f(tan x) = __.",
        "options": [
          "0",
          "-1",
          "1",
          "2"
        ],
        "answer": "2",
        "category": "unattempted",
        "selectedOption": ""
      },
      {
        "question": "d/dx [tan^{-1} x] = __.",
        "options": [
          "1/(1+x^2)",
          "x/(1+x^2)",
          "sin^2 x",
          "cos^2 x"
        ],
        "answer": "1/(1+x^2)",
        "category": "unattempted",
        "selectedOption": ""
      },
      {
        "question": "If f(x) = tan^{-1} x then f(tan x) = __.",
        "options": [
          "0",
          "-1",
          "1",
          "2"
        ],
        "answer": "2",
        "category": "unattempted",
        "selectedOption": ""
      },
      {
        "question": "∫ x^2 dx = __.",
        "options": [
          "x^3/3 + C",
          "x^3 + C",
          "x^2 + C",
          "None of these"
        ],
        "answer": "x^3/3 + C",
        "category": "unattempted",
        "selectedOption": ""
      },
      {
        "question": "f(x) = 3x^2 + 2x + 1. Then ∫{1}^{2} f(x) dx = ___.",
        "options": [
          "11",
          "16",
          "10",
          "15"
        ],
        "answer": "16",
        "category": "unattempted",
        "selectedOption": ""
      },
      {
        "question": "The derivative of f(x) = e^x with respect to x is:",
        "options": [
          "e^x",
          "ln(x)",
          "cos(x)",
          "e^{-x}"
        ],
        "answer": "e^x",
        "category": "unattempted",
        "selectedOption": ""
      },
      {
        "question": "The indefinite integral of 1/x with respect to x is:",
        "options": [
          "ln(x)",
          "x^2",
          "cos(x)",
          "e^{-x}"
        ],
        "answer": "ln(x)",
        "category": "unattempted",
        "selectedOption": ""
      },
      {
        "question": "The integral of sin(x) with respect to x over the interval [0, π] is:",
        "options": [
          "π",
          "-π",
          "1",
          "-1"
        ],
        "answer": "1",
        "category": "unattempted",
        "selectedOption": ""
      },
      {
        "question": "The integral of e^x with respect to x over the interval [0, 1] is:",
        "options": [
          "e",
          "e - 1",
          "e^2",
          "e^2 - 1"
        ],
        "answer": "e - 1",
        "category": "unattempted",
        "selectedOption": ""
      },
      {
        "question": "The derivative of ln(x) with respect to x is:",
        "options": [
          "1/x",
          "x",
          "e^x",
          "1/e^x"
        ],
        "answer": "1/x",
        "category": "unattempted",
        "selectedOption": ""
      },
      {
        "question": "The indefinite integral of cos(x) with respect to x is:",
        "options": [
          "sin(x)",
          "1/sin(x)",
          "-sin(x)",
          "sin^{-1}(x)"
        ],
        "answer": "sin(x)",
        "category": "unattempted",
        "selectedOption": ""
      },
      {
        "question": "The integral of 1/(1 + x^2) with respect to x is:",
        "options": [
          "tan^{-1}(x)",
          "1/tan(x)",
          "cot^{-1}(x)",
          "1/cot(x)"
        ],
        "answer": "tan^{-1}(x)",
        "category": "unattempted",
        "selectedOption": ""
      },
      {
        "question": "The derivative of sin(x) with respect to x is:",
        "options": [
          "cos(x)",
          "1/cos(x)",
          "-cos(x)",
          "sin^{-1}(x)"
        ],
        "answer": "cos(x)",
        "category": "unattempted",
        "selectedOption": ""
      },
      {
        "question": "The indefinite integral of 1/x^2 with respect to x is:",
        "options": [
          "-1/x",
          "x^{-1}",
          "ln(x)",
          "e^{-x}"
        ],
        "answer": "-1/x",
        "category": "unattempted",
        "selectedOption": ""
      },
      {
        "question": "The integral of e^{-x} with respect to x over the interval [0, ∞) is:",
        "options": [
          "1",
          "e",
          "0",
          "-e"
        ],
        "answer": "1",
        "category": "unattempted",
        "selectedOption": ""
      },
      {
        "question": "If tan(θ) = 3/4 and tan(φ) = 4/3, what is θ + φ?",
        "options": [
          "45°",
          "60°",
          "90°",
          "120°"
        ],
        "category": "unattempted",
        "selectedOption": ""
      },
      {
        "question": "What is the equation of the line parallel to the x-axis and passing through the point (2,3)?",
        "options": [
          "y = 2",
          "x = 3",
          "y = 3",
          "x = 2"
        ],
        "category": "unattempted",
        "selectedOption": ""
      },
      {
        "question": "Solve the equation log₂(x + 1) = 2.",
        "options": [
          "x = 3",
          "x = 4",
          "x = 5",
          "x = 6"
        ],
        "category": "unattempted",
        "selectedOption": ""
      },
      {
        "question": "Find the value of sin(180° + φ).",
        "options": [
          "sin φ",
          "-sin φ",
          "cos φ",
          "-cos φ"
        ],
        "category": "unattempted",
        "selectedOption": ""
      },
      {
        "question": "If cos(θ) = 3/5 and θ is acute, what is sin(θ)?",
        "options": [
          "4/5",
          "3/4",
          "4/3",
          "5/3"
        ],
        "category": "unattempted",
        "selectedOption": ""
      },
      {
        "question": "What is the equation of the line passing through the points (-1,2) and (3,-4)?",
        "options": [
          "y = -2x - 4",
          "y = -2x + 4",
          "y = 2x - 4",
          "y = 2x + 4"
        ],
        "category": "unattempted",
        "selectedOption": ""
      },
      {
        "question": "Find the value of 1 - cos²θ.",
        "options": [
          "sin φ",
          "cos φ",
          "tan φ",
          "cot φ"
        ],
        "category": "unattempted",
        "selectedOption": ""
      },
      {
        "question": "Which equation represents the circle passing through the points (-1,0), (0,-1), and (1,0)?",
        "options": [
          "x² + y² = 1",
          "x² + y² = 2",
          "x² + y² = 3",
          "x² + y² = 4"
        ],
        "category": "unattempted",
        "selectedOption": ""
      },
      {
        "question": "What is the value of log₁₀1000?",
        "options": [
          "1",
          "2",
          "3",
          "4"
        ],
        "category": "unattempted",
        "selectedOption": ""
      },
      {
        "question": "Calculate the area of a circle with circumference 10π.",
        "options": [
          "25π",
          "50π",
          "100π",
          "125π"
        ],
        "category": "unattempted",
        "selectedOption": ""
      },
      {
        "question": "Determine the value of tan(30°) cot(30°).",
        "options": [
          "0",
          "1",
          "√3",
          "1/√3"
        ],
        "category": "unattempted",
        "selectedOption": ""
      },
      {
        "question": "What is the derivative of y = 1/x with respect to x?",
        "options": [
          "-1/x²",
          "1/x²",
          "-x",
          "x"
        ],
        "category": "unattempted",
        "selectedOption": ""
      },
      {
        "question": "Given the integral ∫(e^x - e^(-x))/(e^x + e^(-x)) dx, the correct answer is:",
        "options": [
          "arctan(x) + C",
          "arcsin(x) + C",
          "arccos(x) + C",
          "arctanh(x) + C"
        ],
        "answer": "arctanh(x) + C",
        "category": "unattempted",
        "selectedOption": ""
      },
      {
        "question": "Given the integral ∫(e^x (arctanh(x) + 1))/(1 - x^2) dx, the correct answer is:",
        "options": [
          "e^x coth^(-1)(x) + C",
          "e^x arccoth(x) + C",
          "e^x arctan(x) + C",
          "e^x arcsinh(x) + C"
        ],
        "answer": "e^x arccoth(x) + C",
        "category": "unattempted",
        "selectedOption": ""
      },
      {
        "question": "Given the integral ∫(2/x^2) dx, the correct answer is:",
        "options": [
          "2",
          "2/3",
          "3",
          "None of these"
        ],
        "answer": "2/3",
        "category": "unattempted",
        "selectedOption": ""
      },
      {
        "question": "The midpoint of the line segment joining the points A(-B, 3) and B(2, -1) is:",
        "options": [
          "(B/2, 1)",
          "(B/2, -1)",
          "(3 - B/2, 1)",
          "(-5, 2)"
        ],
        "answer": "(-5, 2)",
        "category": "unattempted",
        "selectedOption": ""
      },
      {
        "question": "The latus rectum of the parabola x^2 = -4ay is:",
        "options": [
          "x = a",
          "y = a",
          "x = -a",
          "y = -a"
        ],
        "answer": "y = -a",
        "category": "unattempted",
        "selectedOption": ""
      },
      {
        "question": "The vertices of the ellipse 4x^2 + 9y^2 = 36 are:",
        "options": [
          "(±3, 2)",
          "(±5, 0)",
          "(0, ±3)",
          "(0, ±2)"
        ],
        "answer": "(±5, 0)",
        "category": "unattempted",
        "selectedOption": ""
      },
      {
        "question": "The magnitude of the vector r = a₁i + a₂j + a₃k is:",
        "options": [
          "a₁ + a₂ + a₃",
          "√(a₁^2 + a₂^2 + a₃^2)",
          "√(a₁^2 - a₂^2 - a₃^2)",
          "a₁a₂a₃"
        ],
        "answer": "√(a₁^2 + a₂^2 + a₃^2)",
        "category": "unattempted",
        "selectedOption": ""
      },
      {
        "question": "If the dot product of two vectors is zero, then the vectors are:",
        "options": [
          "Parallel",
          "Perpendicular",
          "Orthogonal",
          "Collinear"
        ],
        "answer": "Perpendicular",
        "category": "unattempted",
        "selectedOption": ""
      },
      {
        "question": "If (3i + 9j + 3k) and (-i + 4j - xk) are perpendicular, then x = _.",
        "options": [
          "9",
          "11",
          "-11",
          "-9"
        ],
        "answer": "11",
        "category": "unattempted",
        "selectedOption": ""
      },
      {
        "question": "For all a, b, c ∈ ℝ, if a = b and b = c, then a = c is an example of:",
        "options": [
          "Reflexive property",
          "Symmetric property",
          "Transitive property",
          "Associative property"
        ],
        "answer": "Transitive property",
        "category": "unattempted",
        "selectedOption": ""
      },
      {
        "question": "The value of i^(-3) is:",
        "options": [
          "-i",
          "i",
          "-1",
          "1"
        ],
        "answer": "-i",
        "category": "unattempted",
        "selectedOption": ""
      },
      {
        "question": "If 3x + 4y = 5 and 2x - y = 3, then x = _.",
        "options": [
          "-5/11",
          "-11/5",
          "-3/2",
          "11/5"
        ],
        "answer": "-11/5",
        "category": "unattempted",
        "selectedOption": ""
      },
      {
        "question": "The value of x for which the function f(x) = x^3 - 6x^2 + 11x - 6 attains its maximum is:",
        "options": [
          "1",
          "2",
          "3",
          "4"
        ],
        "answer": "3",
        "category": "unattempted",
        "selectedOption": ""
      },
      {
        "question": "The derivative of y = ln(sin(x)) with respect to x is:",
        "options": [
          "-cot(x)",
          "-csc(x)",
          "-sec(x)",
          "-cos(x)/sin(x)"
        ],
        "answer": "-cos(x)/sin(x)",
        "category": "unattempted",
        "selectedOption": ""
      },
      {
        "question": "The value of sin(a) + cos(a) is:",
        "options": [
          "1",
          "√2",
          "0",
          "2"
        ],
        "answer": "√2",
        "category": "unattempted",
        "selectedOption": ""
      },
      {
        "question": "The distance between the points P(3, 4) and Q(-1, 2) is:",
        "options": [
          "2",
          "3",
          "4",
          "√10"
        ],
        "answer": "√10",
        "category": "unattempted",
        "selectedOption": ""
      },
      {
        "question": "The measure of an exterior angle of a regular polygon is 45°. The number of sides of the polygon is:",
        "options": [
          "6",
          "8",
          "10",
          "12"
        ],
        "answer": "8",
        "category": "unattempted",
        "selectedOption": ""
      },
      {
        "question": "The sum of the measures of the angles of a quadrilateral is:",
        "options": [
          "180°",
          "270°",
          "360°",
          "450°"
        ],
        "answer": "360°",
        "category": "unattempted",
        "selectedOption": ""
      },
      {
        "question": "For the function f(x) = (x^2 + 3x + 2) / (x + 2), what is f(0)?",
        "options": [
          "0",
          "1",
          "2",
          "None of these"
        ],
        "answer": "1",
        "category": "unattempted",
        "selectedOption": ""
      },
      {
        "question": "What is the derivative of y = cos^2 x with respect to x?",
        "options": [
          "-2cos x",
          "-2sin x",
          "-2cos x sin x",
          "-2sin x cos x"
        ],
        "answer": "-2cos x sin x",
        "category": "unattempted",
        "selectedOption": ""
      },
      {
        "question": "Determine the value of log_10 0.001.",
        "options": [
          "-3",
          "-2",
          "3",
          "2"
        ],
        "answer": "-3",
        "category": "unattempted",
        "selectedOption": ""
      },
      {
        "question": "Find the angle between the lines 3x + 4y = 5 and 6x - 8y = 10.",
        "options": [
          "0°",
          "45°",
          "90°",
          "180°"
        ],
        "answer": "90°",
        "category": "unattempted",
        "selectedOption": ""
      },
      {
        "question": "If sin(θ) = 3/5 and θ is acute, what is cos(θ)?",
        "options": [
          "4/5",
          "3/4",
          "4/3",
          "5/3"
        ],
        "answer": "4/5",
        "category": "unattempted",
        "selectedOption": ""
      },
      {
        "question": "Evaluate tan(90° - θ).",
        "options": [
          "tan(θ)",
          "-tan(θ)",
          "cot(θ)",
          "-cot(θ)"
        ],
        "answer": "cot(θ)",
        "category": "unattempted",
        "selectedOption": ""
      },
      {
        "question": "What is the sum of the squares of the roots of the equation x^2 - 5x + 6 = 0?",
        "options": [
          "6",
          "5",
          "7",
          "8"
        ],
        "answer": "5",
        "category": "unattempted",
        "selectedOption": ""
      },
      {
        "question": "Determine the value of sin^(-1)(1/2).",
        "options": [
          "30°",
          "45°",
          "60°",
          "90°"
        ],
        "answer": "60°",
        "category": "unattempted",
        "selectedOption": ""
      },
      {
        "question": "What is the equation of the line passing through the points (-1, 2) and (3, -4)?",
        "options": [
          "y = -2x - 4",
          "y = -2x + 4",
          "y = 2x - 4",
          "y = 2x + 4"
        ],
        "answer": "y = -2x - 4",
        "category": "unattempted",
        "selectedOption": ""
      },
      {
        "question": "What is the square root of 1 + sin^2 x?",
        "options": [
          "cos x",
          "sin x",
          "tan x",
          "cot x"
        ],
        "answer": "cos x",
        "category": "unattempted",
        "selectedOption": ""
      },
      {
        "question": "Describe the equation of the circle that passes through the points (-1, 0), (0, -1), and (1, 0).",
        "options": [
          "x^2 + y^2 = 1",
          "x^2 + y^2 = 2",
          "x^2 + y^2 = 3",
          "x^2 + y^2 = 4"
        ],
        "answer": "x^2 + y^2 = 2",
        "category": "unattempted",
        "selectedOption": ""
      },
      {
        "question": "What is the logarithm base 10 of 1000?",
        "options": [
          "1",
          "2",
          "3",
          "4"
        ],
        "answer": "3",
        "category": "unattempted",
        "selectedOption": ""
      },
      {
        "question": "Find the area of a circle with circumference 10π.",
        "options": [
          "25π",
          "50π",
          "100π",
          "125π"
        ],
        "answer": "50π",
        "category": "unattempted",
        "selectedOption": ""
      },
      {
        "question": "Evaluate tan 30° / cot 30°.",
        "options": [
          "0",
          "1",
          "√3",
          "1/√3"
        ],
        "answer": "1",
        "category": "unattempted",
        "selectedOption": ""
      },
      {
        "question": "What is the derivative of y = 1 / x with respect to x?",
        "options": [
          "-1 / x^2",
          "1 / x^2",
          "-x",
          "x"
        ],
        "answer": "-1 / x^2",
        "category": "unattempted",
        "selectedOption": ""
      },
      {
        "question": "If tan A = 3/4 and tan B = 4/3, what is A + B?",
        "options": [
          "45°",
          "60°",
          "90°",
          "120°"
        ],
        "answer": "90°",
        "category": "unattempted",
        "selectedOption": ""
      },
      {
        "question": "Describe the equation of the line that is parallel to the x-axis and passes through the point (2, 3).",
        "options": [
          "y = 2",
          "x = 3",
          "y = 3",
          "x = 2"
        ],
        "answer": "y = 3",
        "category": "unattempted",
        "selectedOption": ""
      },
      {
        "question": "Solve the equation log_2(x + 1) = 2.",
        "options": [
          "x = 3",
          "x = 4",
          "x = 5",
          "x = 6"
        ],
        "answer": "x = 4",
        "category": "unattempted",
        "selectedOption": ""
      },
      {
        "question": "What is sin(180° + θ)?",
        "options": [
          "sin θ",
          "-sin θ",
          "cos θ",
          "-cos θ"
        ],
        "answer": "sin θ",
        "category": "unattempted",
        "selectedOption": ""
      },
      {
        "question": "What is the derivative of f(x) = e^x with respect to x?",
        "options": [
          "e^x",
          "ln(x)",
          "cos(x)",
          "e^{-x}"
        ],
        "answer": "e^x",
        "category": "unattempted",
        "selectedOption": ""
      },
      {
        "question": "The indefinite integral of 1/x with respect to x is:",
        "options": [
          "ln(x)",
          "x^2",
          "cos(x)",
          "e^{-x}"
        ],
        "answer": "ln(x)",
        "category": "unattempted",
        "selectedOption": ""
      },
      {
        "question": "The integral of sin(x) with respect to x over the interval [0, π] is:",
        "options": [
          "π",
          "-π",
          "1",
          "-1"
        ],
        "answer": "1",
        "category": "unattempted",
        "selectedOption": ""
      },
      {
        "question": "The integral of e^x with respect to x over the interval [0, 1] is:",
        "options": [
          "e",
          "e - 1",
          "e^2",
          "e^2 - 1"
        ],
        "answer": "e - 1",
        "category": "unattempted",
        "selectedOption": ""
      },
      {
        "question": "The derivative of ln(x) with respect to x is:",
        "options": [
          "1/x",
          "x",
          "e^x",
          "1/e^x"
        ],
        "answer": "1/x",
        "category": "unattempted",
        "selectedOption": ""
      },
      {
        "question": "The indefinite integral of cos(x) with respect to x is:",
        "options": [
          "sin(x)",
          "1/sin(x)",
          "-sin(x)",
          "sin^{-1}(x)"
        ],
        "answer": "sin(x)",
        "category": "unattempted",
        "selectedOption": ""
      },
      {
        "question": "The integral of 1/(1 + x^2) with respect to x is:",
        "options": [
          "tan^{-1}(x)",
          "1/tan(x)",
          "cot^{-1}(x)",
          "1/cot(x)"
        ],
        "answer": "tan^{-1}(x)",
        "category": "unattempted",
        "selectedOption": ""
      }
    ]
  }
]